webhooks/__init__.py
robotframework_webhooks-1.1.9.dist-info/LICENSE
robotframework_webhooks-1.1.9.dist-info/METADATA
robotframework_webhooks-1.1.9.dist-info/WHEEL
robotframework_webhooks-1.1.9.dist-info/top_level.txt
robotframework_webhooks-1.1.9.dist-info/RECORD
