Metadata-Version: 2.1
Name: robotframework-webhooks
Version: 1.1.9
Summary: A listener that sends a Stack Trace to MS-Teams when a test in Robot framework fails
Home-page: https://github.com/Alpha-Centauri-00/robotframework-webhooks
Author: M.Kherki(Alpha-Centauri-00)
Author-email: alpha_Centauri@posteo.de
Classifier: Programming Language :: Python :: 3
Classifier: License :: OSI Approved :: MIT License
Classifier: Operating System :: OS Independent
Classifier: Topic :: Software Development :: Testing
Classifier: Topic :: Software Development :: Testing :: Acceptance
Classifier: Framework :: Robot Framework
Requires-Python: >=3.6
License-File: LICENSE
Requires-Dist: robotframework >=3.2
Requires-Dist: toml
Requires-Dist: requests
